pb_graphene/__init__.py
pb_graphene/global_id.py
pb_graphene/django/__init__.py
pb_graphene/django/mutation.py
pb_graphene-0.0.2.dist-info/LICENSE
pb_graphene-0.0.2.dist-info/METADATA
pb_graphene-0.0.2.dist-info/WHEEL
pb_graphene-0.0.2.dist-info/top_level.txt
pb_graphene-0.0.2.dist-info/RECORD
